MANIFEST.in
README.rst
s3logs.py
setup.py
s3logs.egg-info/PKG-INFO
s3logs.egg-info/SOURCES.txt
s3logs.egg-info/dependency_links.txt
s3logs.egg-info/entry_points.txt
s3logs.egg-info/requires.txt
s3logs.egg-info/top_level.txt