Metadata-Version: 1.1
Name: s3logs
Version: 1.8
Summary: Push logs to S3
Home-page: https://github.com/m-messiah/s3logs
Author: m_messiah
Author-email: m.muzafarov@gmail.com
License: MIT
Keywords: logs s3 nginx
Platform: UNKNOWN
Classifier: Development Status :: 5 - Production/Stable
Classifier: Intended Audience :: System Administrators
Classifier: Topic :: Utilities
Classifier: License :: OSI Approved :: MIT License
Classifier: Programming Language :: Python :: 2.7
Classifier: Programming Language :: Python :: 3
